ex4.1/ex401.sv
module sillyfunction(
    input logic a, b, c,
    output logic y);

    assign y = ~a & ~b & ~c |
                a & ~b & ~c |
                a & ~b & c;

endmodule

ex4.1/ex401_tb.sv
`timescale 10ns/10ns

module tb01();
    logic a, b, c, y;

    sillyfunction dut(a, b, c, y);
    
    initial begin
        $dumpfile("ex401.vcd");
        $dumpvars(0,tb01);
        $monitor($stime, a, b, c, y);
        a = 0; b = 0; c = 0;    #10;
        c = 1;                  #10;
        b = 1; c = 0;           #10;
        c = 1;                  #10;
        a = 1; b = 0; c = 0;    #10;
        c = 1;                  #10;
        b = 1; c = 0;           #10;
        c = 1;                  #10;
    end
endmodule

ex4.1/ex401.vcd
$date
	Mon Jul  1 10:18:27 2024
$end
$version
	Icarus Verilog
$end
$timescale
	10ns
$end
$scope module tb01 $end
$var wire 1 ! y $end
$var reg 1 " a $end
$var reg 1 # b $end
$var reg 1 $ c $end
$scope module dut $end
$var wire 1 " a $end
$var wire 1 # b $end
$var wire 1 $ c $end
$var wire 1 ! y $end
$upscope $end
$upscope $end
$enddefinitions $end
$comment Show the parameter values. $end
$dumpall
$end
#0
$dumpvars
0$
0#
0"
1!
$end
#10
0!
1$
#20
0$
1#
#30
1$
#40
1!
0$
0#
1"
#50
1$
#60
0!
0$
1#
#70
1$
