ex4.13/ex413.sv
`timescale 1ns/1ps

module example(input  logic a, b, c,
               output logic y);
    logic ab, bb, cb, n1, n2, n3;
    assign #1 {ab, bb, cb} = ~{a, b, c};
    assign #2 n1 = ab & bb & cb;
    assign #2 n2 = a & bb & cb;
    assign #2 n3 = a & bb & c;
    assign #4 y = n1 | n2 | n3;
endmodule

ex4.13/ex413_tb.sv
`timescale 1ns/1ns

module tb13();
    logic a, b, c, y;

    example dut(a, b, c, y);

    initial begin
        $dumpfile("ex413.vcd");
        $dumpvars(0, dut);
        a = 0; b = 0; c = 0; #10;
        a = 0; b = 0; c = 1; #10;
        a = 0; b = 1; c = 0; #10;
        a = 0; b = 1; c = 1; #10;
        a = 1; b = 0; c = 0; #10;
        a = 1; b = 0; c = 1; #10;
        a = 1; b = 1; c = 0; #10;
        a = 1; b = 1; c = 1; #10;
    end
endmodule

ex4.13/ex413.vcd
$date
	Sun Jul 07 22:36:27 2024
$end
$version
	Icarus Verilog
$end
$timescale
	1ps
$end
$scope module tb13 $end
$scope module dut $end
$var wire 1 ! a $end
$var wire 1 " b $end
$var wire 1 # c $end
$var wire 1 $ n1 $end
$var wire 1 % n2 $end
$var wire 1 & n3 $end
$var wire 1 ' y $end
$var wire 1 ( cb $end
$var wire 1 ) bb $end
$var wire 1 * ab $end
$upscope $end
$upscope $end
$enddefinitions $end
$comment Show the parameter values. $end
$dumpall
$end
#0
$dumpvars
x*
x)
x(
x'
x&
x%
x$
0#
0"
0!
$end
#1000
1*
1)
1(
#2000
0&
0%
#3000
1$
#7000
1'
#10000
1#
#11000
0(
#13000
0$
#17000
0'
#20000
0#
1"
#21000
0)
1(
#30000
1#
#31000
0(
#40000
0#
0"
1!
#41000
0*
1)
1(
#43000
1%
#47000
1'
#50000
1#
#51000
0(
#52000
1&
#53000
0%
#60000
0#
1"
#61000
0)
1(
#62000
0&
#66000
0'
#70000
1#
#71000
0(
